<?xml version="1.0" encoding="UTF-8"?>
<con:soapui-project id="6e0277fc-bac9-48f3-a49d-2df88d8dab34" activeEnvironment="Default" name="NumberConversion" resourceRoot="" soapui-version="5.6.0" abortOnError="false" runType="SEQUENTIAL" xmlns:con="http://eviware.com/soapui/config"><con:settings/><con:interface xsi:type="con:WsdlInterface" id="f2150976-d57c-4f2b-9762-e92a25086ffa" wsaVersion="NONE" name="NumberConversionSoapBinding" type="wsdl" bindingName="{http://www.dataaccess.com/webservicesserver/}NumberConversionSoapBinding" soapVersion="1_1" anonymous="optional" definition="https://www.dataaccess.com/webservicesserver/numberconversion.wso?WSDL" xmlns:xsi="http://www.w3.org/2001/XMLSchema-instance"><con:settings/><con:definitionCache/><con:endpoints><con:endpoint>https://www.dataaccess.com/webservicesserver/numberconversion.wso</con:endpoint></con:endpoints><con:operation id="1b73fd52-d12d-4a78-a56e-c98e27a8f2ab" isOneWay="false" action="" name="NumberToDollars" bindingOperationName="NumberToDollars" type="Request-Response" inputName="" receivesAttachments="false" sendsAttachments="false" anonymous="optional"><con:settings/><con:call id="1e87f1ed-eb08-45c4-bf50-6d27761c2143" name="Request 1"><con:settings/><con:encoding>UTF-8</con:encoding><con:endpoint>https://www.dataaccess.com/webservicesserver/numberconversion.wso</con:endpoint><con:request><![CDATA[<soapenv:Envelope xmlns:soapenv="http://schemas.xmlsoap.org/soap/envelope/" xmlns:web="http://www.dataaccess.com/webservicesserver/">\r
   <soapenv:Header/>\r
   <soapenv:Body>\r
      <web:NumberToDollars>\r
         <web:dNum>?</web:dNum>\r
      </web:NumberToDollars>\r
   </soapenv:Body>\r
</soapenv:Envelope>]]></con:request><con:wsaConfig mustUnderstand="NONE" version="200508" action="http://www.dataaccess.com/webservicesserver/NumberConversionSoapType/NumberToDollarsRequest"/></con:call></con:operation><con:operation id="7aa1177d-7889-4813-a9ba-3cd87cabce32" isOneWay="false" action="" name="NumberToWords" bindingOperationName="NumberToWords" type="Request-Response" inputName="" receivesAttachments="false" sendsAttachments="false" anonymous="optional"><con:settings/><con:call id="ba0de30d-5ffe-43aa-bed5-c28692bf8e8d" name="Request 1"><con:settings><con:setting id="com.eviware.soapui.impl.wsdl.WsdlRequest@request-headers">&lt;xml-fragment/></con:setting></con:settings><con:encoding>UTF-8</con:encoding><con:endpoint>https://www.dataaccess.com/webservicesserver/numberconversion.wso</con:endpoint><con:request><![CDATA[<soapenv:Envelope xmlns:soapenv="http://schemas.xmlsoap.org/soap/envelope/" xmlns:web="http://www.dataaccess.com/webservicesserver/">\r
   <soapenv:Header/>\r
   <soapenv:Body>\r
      <web:NumberToWords>\r
         <web:ubiNum>23</web:ubiNum>\r
      </web:NumberToWords>\r
   </soapenv:Body>\r
</soapenv:Envelope>]]></con:request><con:credentials><con:authType>No Authorization</con:authType></con:credentials><con:jmsConfig JMSDeliveryMode="PERSISTENT"/><con:jmsPropertyConfig/><con:wsaConfig mustUnderstand="NONE" version="200508" action="http://www.dataaccess.com/webservicesserver/NumberConversionSoapType/NumberToWordsRequest"/><con:wsrmConfig version="1.2"/></con:call></con:operation></con:interface><con:interface xsi:type="con:WsdlInterface" id="f759a3ea-4b56-401e-ab55-5d44e61460c7" wsaVersion="NONE" name="NumberConversionSoapBinding12" type="wsdl" bindingName="{http://www.dataaccess.com/webservicesserver/}NumberConversionSoapBinding12" soapVersion="1_2" anonymous="optional" definition="https://www.dataaccess.com/webservicesserver/numberconversion.wso?WSDL" xmlns:xsi="http://www.w3.org/2001/XMLSchema-instance"><con:settings/><con:definitionCache type="TEXT" rootPart="https://www.dataaccess.com/webservicesserver/numberconversion.wso?WSDL"><con:part><con:url>https://www.dataaccess.com/webservicesserver/numberconversion.wso?WSDL</con:url><con:content><![CDATA[<definitions name="NumberConversion" targetNamespace="http://www.dataaccess.com/webservicesserver/" xmlns="http://schemas.xmlsoap.org/wsdl/" xmlns:xs="http://www.w3.org/2001/XMLSchema" xmlns:soap="http://schemas.xmlsoap.org/wsdl/soap/" xmlns:soap12="http://schemas.xmlsoap.org/wsdl/soap12/" xmlns:tns="http://www.dataaccess.com/webservicesserver/">
  <types>
    <xs:schema elementFormDefault="qualified" targetNamespace="http://www.dataaccess.com/webservicesserver/">
      <xs:element name="NumberToWords">
        <xs:complexType>
          <xs:sequence>
            <xs:element name="ubiNum" type="xs:unsignedLong"/>
          </xs:sequence>
        </xs:complexType>
      </xs:element>
      <xs:element name="NumberToWordsResponse">
        <xs:complexType>
          <xs:sequence>
            <xs:element name="NumberToWordsResult" type="xs:string"/>
          </xs:sequence>
        </xs:complexType>
      </xs:element>
      <xs:element name="NumberToDollars">
        <xs:complexType>
          <xs:sequence>
            <xs:element name="dNum" type="xs:decimal"/>
          </xs:sequence>
        </xs:complexType>
      </xs:element>
      <xs:element name="NumberToDollarsResponse">
        <xs:complexType>
          <xs:sequence>
            <xs:element name="NumberToDollarsResult" type="xs:string"/>
          </xs:sequence>
        </xs:complexType>
      </xs:element>
    </xs:schema>
  </types>
  <message name="NumberToWordsSoapRequest">
    <part name="parameters" element="tns:NumberToWords"/>
  </message>
  <message name="NumberToWordsSoapResponse">
    <part name="parameters" element="tns:NumberToWordsResponse"/>
  </message>
  <message name="NumberToDollarsSoapRequest">
    <part name="parameters" element="tns:NumberToDollars"/>
  </message>
  <message name="NumberToDollarsSoapResponse">
    <part name="parameters" element="tns:NumberToDollarsResponse"/>
  </message>
  <portType name="NumberConversionSoapType">
    <operation name="NumberToWords">
      <documentation>Returns the word corresponding to the positive number passed as parameter. Limited to quadrillions.</documentation>
      <input message="tns:NumberToWordsSoapRequest"/>
      <output message="tns:NumberToWordsSoapResponse"/>
    </operation>
    <operation name="NumberToDollars">
      <documentation>Returns the non-zero dollar amount of the passed number.</documentation>
      <input message="tns:NumberToDollarsSoapRequest"/>
      <output message="tns:NumberToDollarsSoapResponse"/>
    </operation>
  </portType>
  <binding name="NumberConversionSoapBinding" type="tns:NumberConversionSoapType">
    <soap:binding style="document" transport="http://schemas.xmlsoap.org/soap/http"/>
    <operation name="NumberToWords">
      <soap:operation soapAction="" style="document"/>
      <input>
        <soap:body use="literal"/>
      </input>
      <output>
        <soap:body use="literal"/>
      </output>
    </operation>
    <operation name="NumberToDollars">
      <soap:operation soapAction="" style="document"/>
      <input>
        <soap:body use="literal"/>
      </input>
      <output>
        <soap:body use="literal"/>
      </output>
    </operation>
  </binding>
  <binding name="NumberConversionSoapBinding12" type="tns:NumberConversionSoapType">
    <soap12:binding style="document" transport="http://schemas.xmlsoap.org/soap/http"/>
    <operation name="NumberToWords">
      <soap12:operation soapAction="" style="document"/>
      <input>
        <soap12:body use="literal"/>
      </input>
      <output>
        <soap12:body use="literal"/>
      </output>
    </operation>
    <operation name="NumberToDollars">
      <soap12:operation soapAction="" style="document"/>
      <input>
        <soap12:body use="literal"/>
      </input>
      <output>
        <soap12:body use="literal"/>
      </output>
    </operation>
  </binding>
  <service name="NumberConversion">
    <documentation>The Number Conversion Web Service, implemented with DataFlex, provides functions that convert numbers into words or dollar amounts.</documentation>
    <port name="NumberConversionSoap" binding="tns:NumberConversionSoapBinding">
      <soap:address location="https://www.dataaccess.com/webservicesserver/numberconversion.wso"/>
    </port>
    <port name="NumberConversionSoap12" binding="tns:NumberConversionSoapBinding12">
      <soap12:address location="https://www.dataaccess.com/webservicesserver/numberconversion.wso"/>
    </port>
  </service>
</definitions>]]></con:content><con:type>http://schemas.xmlsoap.org/wsdl/</con:type></con:part></con:definitionCache><con:endpoints><con:endpoint>https://www.dataaccess.com/webservicesserver/numberconversion.wso</con:endpoint></con:endpoints><con:operation id="75e02ccb-b4ad-4bdf-9977-1a37e43ab945" isOneWay="false" action="" name="NumberToDollars" bindingOperationName="NumberToDollars" type="Request-Response" inputName="" receivesAttachments="false" sendsAttachments="false" anonymous="optional"><con:settings/><con:call id="a8f4d4aa-7b7e-4303-881e-7e9267aee7e8" name="Request 1"><con:settings/><con:encoding>UTF-8</con:encoding><con:endpoint>https://www.dataaccess.com/webservicesserver/numberconversion.wso</con:endpoint><con:request><![CDATA[<soap:Envelope xmlns:soap="http://www.w3.org/2003/05/soap-envelope" xmlns:web="http://www.dataaccess.com/webservicesserver/">\r
   <soap:Header/>\r
   <soap:Body>\r
      <web:NumberToDollars>\r
         <web:dNum>?</web:dNum>\r
      </web:NumberToDollars>\r
   </soap:Body>\r
</soap:Envelope>]]></con:request><con:wsaConfig mustUnderstand="NONE" version="200508" action="http://www.dataaccess.com/webservicesserver/NumberConversionSoapType/NumberToDollarsRequest"/></con:call></con:operation><con:operation id="ecfc341b-ba87-42d3-935d-3bae06188664" isOneWay="false" action="" name="NumberToWords" bindingOperationName="NumberToWords" type="Request-Response" inputName="" receivesAttachments="false" sendsAttachments="false" anonymous="optional"><con:settings/><con:call id="6f512591-a340-48e6-adf7-dadda676179b" name="Request 1"><con:settings/><con:encoding>UTF-8</con:encoding><con:endpoint>https://www.dataaccess.com/webservicesserver/numberconversion.wso</con:endpoint><con:request><![CDATA[<soap:Envelope xmlns:soap="http://www.w3.org/2003/05/soap-envelope" xmlns:web="http://www.dataaccess.com/webservicesserver/">\r
   <soap:Header/>\r
   <soap:Body>\r
      <web:NumberToWords>\r
         <web:ubiNum>?</web:ubiNum>\r
      </web:NumberToWords>\r
   </soap:Body>\r
</soap:Envelope>]]></con:request><con:wsaConfig mustUnderstand="NONE" version="200508" action="http://www.dataaccess.com/webservicesserver/NumberConversionSoapType/NumberToWordsRequest"/></con:call></con:operation></con:interface><con:testSuite id="eed1d0fa-1c65-47a9-85ea-f92da31b00ec" name="TestSuite 1"><con:settings/><con:runType>SEQUENTIAL</con:runType><con:testCase id="f316b83d-b441-4bdc-87aa-0c3bc1d5b53d" failOnError="true" failTestCaseOnErrors="true" keepSession="false" maxResults="0" name="TestCase 1" searchProperties="true"><con:settings/><con:testStep type="groovy" name="Groovy Script" id="d9fe8721-f10f-4657-ae55-d2386bf39293"><con:settings/><con:config><script>import jxl.*
import jxl.write.*
import java.io.File;
import com.eviware.soapui.support.*;
import java.util.*;
import java.lang.*;

// import Java Excel API library
def TestCase = context.testCase

def count
Workbook WorkBook1 = Workbook.getWorkbook(new File("C:\\repo\\Book1.xls"))
Sheet Sheet1 = WorkBook1.getSheet(0)
PropertiesTestStep = TestCase.getTestStepByName("Properties")
count = PropertiesTestStep.getPropertyValue("Counter").toInteger()
//If Total records is unknown (at start), get the rowcount from Excel
if (PropertiesTestStep.getPropertyValue("Total").toString() == "")
    PropertiesTestStep.setPropertyValue("Total", Sheet1.getRows().toString())
count++
//Read the Excel test data
Cell Field1 = Sheet1.getCell(0, count)
Cell Field2 = Sheet1.getCell(1, count)
log.info ("Count is " + count.toString() + " Number : " + Field1.getContents() + " Word : " + Field2.getContents())
WorkBook1.close()
//Copy the Excel test data to properties in Properties test step
PropertiesTestStep.setPropertyValue("Number", Field1.getContents())
PropertiesTestStep.setPropertyValue("Word", Field2.getContents())
PropertiesTestStep.setPropertyValue("Counter", count.toString())
if (count == PropertiesTestStep.getPropertyValue("Total").toInteger() - 1)
    PropertiesTestStep.setPropertyValue("End", "True")
</script></con:config></con:testStep><con:testStep type="properties" name="Properties" id="dd9deb53-fe1f-4110-a30e-e263d9322b4e"><con:settings/><con:config xsi:type="con:PropertiesStep" saveFirst="true" xmlns:xsi="http://www.w3.org/2001/XMLSchema-instance"><con:properties><con:property><con:name>Number</con:name><con:value/></con:property><con:property><con:name>Word</con:name><con:value/></con:property><con:property><con:name>Counter</con:name><con:value/></con:property><con:property><con:name>Total</con:name><con:value/></con:property><con:property><con:name>End</con:name><con:value>False</con:value></con:property></con:properties></con:config></con:testStep><con:testStep type="request" id="0c5f18d0-2032-481c-8888-b12d3f576870" name="NumberToWords"><con:settings/><con:config xsi:type="con:RequestStep" xmlns:xsi="http://www.w3.org/2001/XMLSchema-instance"><con:interface>NumberConversionSoapBinding</con:interface><con:operation>NumberToWords</con:operation><con:request name="NumberToWords" outgoingWss="" incomingWss="" timeout="" sslKeystore="" useWsAddressing="false" useWsReliableMessaging="false" wssPasswordType="" id="f04ea963-a20d-4d75-9694-c7c6692fd342"><con:settings><con:setting id="com.eviware.soapui.impl.wsdl.WsdlRequest@request-headers">&lt;xml-fragment/></con:setting></con:settings><con:encoding>UTF-8</con:encoding><con:endpoint>https://www.dataaccess.com/webservicesserver/numberconversion.wso</con:endpoint><con:request><![CDATA[<soapenv:Envelope xmlns:soapenv="http://schemas.xmlsoap.org/soap/envelope/" xmlns:web="http://www.dataaccess.com/webservicesserver/">\r
   <soapenv:Header/>\r
   <soapenv:Body>\r
      <web:NumberToWords>\r
         <web:ubiNum>${Properties#Number}</web:ubiNum>\r
      </web:NumberToWords>\r
   </soapenv:Body>\r
</soapenv:Envelope>	]]></con:request><con:assertion type="SOAP Response" id="1a1c4861-c91f-405f-a838-ed9745b29aa0" name="SOAP Response"/><con:assertion type="Simple Contains" id="80c338cf-39dc-4409-826c-48607ecfb148" name="Contains"><con:configuration><token>${Properties#Word}</token><ignoreCase>false</ignoreCase><useRegEx>false</useRegEx></con:configuration></con:assertion><con:credentials><con:authType>No Authorization</con:authType></con:credentials><con:jmsConfig JMSDeliveryMode="PERSISTENT"/><con:jmsPropertyConfig/><con:wsaConfig mustUnderstand="NONE" version="200508" action="http://www.dataaccess.com/webservicesserver/NumberConversionSoapType/NumberToWordsRequest"/><con:wsrmConfig version="1.2"/></con:request></con:config></con:testStep><con:testStep type="groovy" name="Groovy Script- DataLoop" id="9637601d-2259-4e0d-9417-eda28bd9c456"><con:settings/><con:config><script>def TestCase = context.testCase
PropertiesTestStep = TestCase.getTestStepByName("Properties")
Stop = PropertiesTestStep.getPropertyValue("End").toString()
if (Stop=="True")
    log.info("Exit Groovy Script - DataLoop")
else
    testRunner.gotoStepByName("Groovy Script")</script></con:config></con:testStep><con:properties/></con:testCase><con:properties/></con:testSuite><con:properties/><con:wssContainer/><con:oAuth2ProfileContainer/><con:oAuth1ProfileContainer/></con:soapui-project>